Metadata-Version: 1.1
Name: libgff
Version: 0.2.0
Summary: A library for handling GTF/GFF/GFF3 files
Home-page: https://github.com/antonybholmes/libgff
Author: Antony B Holmes
Author-email: antony.b.holmes@gmail.com
License: UNKNOWN
Platform: UNKNOWN
Classifier: Programming Language :: Python :: 3
Classifier: License :: OSI Approved :: MIT License
Classifier: Operating System :: OS Independent
